aidefense/__init__.py
aidefense/config.py
aidefense/exceptions.py
aidefense/management/__init__.py
aidefense/management/applications.py
aidefense/management/auth.py
aidefense/management/base_client.py
aidefense/management/connections.py
aidefense/management/events.py
aidefense/management/management_client.py
aidefense/management/models/__init__.py
aidefense/management/models/application.py
aidefense/management/models/common.py
aidefense/management/models/connection.py
aidefense/management/models/event.py
aidefense/management/models/policy.py
aidefense/management/models/validation.py
aidefense/management/policies.py
aidefense/management/routes.py
aidefense/management/validation_client.py
aidefense/models/base.py
aidefense/modelscan/README.md
aidefense/modelscan/__init__.py
aidefense/modelscan/model_scan.py
aidefense/modelscan/model_scan_base.py
aidefense/modelscan/models.py
aidefense/modelscan/routes.py
aidefense/request_handler.py
aidefense/runtime/__init__.py
aidefense/runtime/auth.py
aidefense/runtime/chat_inspect.py
aidefense/runtime/chat_models.py
aidefense/runtime/constants.py
aidefense/runtime/http_inspect.py
aidefense/runtime/http_models.py
aidefense/runtime/inspection_client.py
aidefense/runtime/models.py
aidefense/runtime/utils.py
aidefense/tests/test_ai_validation_client.py
aidefense/tests/test_application_management_client.py
aidefense/tests/test_auth.py
aidefense/tests/test_chat_inspect.py
aidefense/tests/test_config.py
aidefense/tests/test_connection_management_client.py
aidefense/tests/test_event_management_client.py
aidefense/tests/test_http_inspect.py
aidefense/tests/test_inspection_client.py
aidefense/tests/test_management_client.py
aidefense/tests/test_policy_management_client.py
aidefense/tests/test_request_handler.py
aidefense/tests/test_routes.py
aidefense/tests/test_utils.py
aidefense/version.py
cisco_aidefense_sdk-2.0.0.dist-info/LICENSE
cisco_aidefense_sdk-2.0.0.dist-info/METADATA
cisco_aidefense_sdk-2.0.0.dist-info/WHEEL
cisco_aidefense_sdk-2.0.0.dist-info/RECORD
