Metadata-Version: 2.1
Name: cisco-aidefense-sdk
Version: 2.0.0
Summary: Cisco AI Defense Python SDK
Author: Shiva Guntoju
Author-email: shguntoj@cisco.com
Requires-Python: >=3.9,<4.0
Classifier: Intended Audience :: Developers
Classifier: Operating System :: OS Independent
Classifier: Programming Language :: Python :: 3
Classifier: Programming Language :: Python :: 3.9
Classifier: Programming Language :: Python :: 3.10
Classifier: Programming Language :: Python :: 3.11
Classifier: Programming Language :: Python :: 3.12
Requires-Dist: pydantic (>=2.12.5,<3.0.0)
Requires-Dist: requests (>=2.32.3,<3.0.0)
Requires-Dist: uuid (>=1.30,<2.0)
